clean_base/__main__.py
clean_base/either.py
clean_base/entities.py
clean_base/exceptions.py
clean_base/lock.py
clean_base/settings.py
clean_base/validations.py
clean_base-0.1.2.dist-info/LICENSE
clean_base-0.1.2.dist-info/METADATA
clean_base-0.1.2.dist-info/WHEEL
clean_base-0.1.2.dist-info/top_level.txt
clean_base-0.1.2.dist-info/RECORD
