Metadata-Version: 2.1
Name: clean-base
Version: 0.1.2
Summary: A simple and lighweight package tor clean softwares.
Author-email: Samuel Galvão Elias <sgelias@outlook.com>
Project-URL: Homepage, https://github.com/sgelias/clean-base-py
Keywords: Bioinformatics,Clean Architecture,Monad Either
Classifier: Programming Language :: Python :: 3.11
Classifier: License :: OSI Approved :: MIT License
Classifier: Operating System :: OS Independent
Classifier: Development Status :: 1 - Planning
Classifier: Intended Audience :: Developers
Classifier: Topic :: Software Development :: Libraries :: Python Modules
Classifier: Topic :: Scientific/Engineering :: Bio-Informatics
Requires-Python: >=3.11
License-File: LICENSE
